{
  "version": "9e040dc6c153",
  "generated": "2026-04-22T23:54:01.951686+02:00",
  "totalCards": 21364,
  "chunks": [
    {
      "file": "cards_chunk_standard.json",
      "era": "standard",
      "count": 3769,
      "hash": "978b686d"
    },
    {
      "file": "cards_chunk_extended.json",
      "era": "extended",
      "count": 4455,
      "hash": "2efaed80"
    },
    {
      "file": "cards_chunk_legacy.json",
      "era": "legacy",
      "count": 13024,
      "hash": "acfe5fea"
    }
  ]
}